comicmeteor/__init__.py
comicmeteor/descramble.py
comicmeteor/retrieve.py
comicmeteor-0.2.dist-info/LICENSE
comicmeteor-0.2.dist-info/METADATA
comicmeteor-0.2.dist-info/WHEEL
comicmeteor-0.2.dist-info/top_level.txt
comicmeteor-0.2.dist-info/RECORD
